davidkhala/purview/__init__.py
davidkhala/purview/const.py
davidkhala/purview/databricks/__init__.py
davidkhala/purview/entity.py
davidkhala/purview/fabric/__init__.py
davidkhala/purview/fabric/powerbi.py
davidkhala/purview/lineage/__init__.py
davidkhala/purview/lineage/databricks.py
davidkhala/purview/lineage/weaver/powerbi.py
davidkhala/purview/relationship.py
davidkhala/purview/scan/__init__.py
davidkhala_purview-0.0.3.dist-info/METADATA
davidkhala_purview-0.0.3.dist-info/WHEEL
davidkhala_purview-0.0.3.dist-info/RECORD
